README.rst
setup.py
RestfulClient/__init__.py
RestfulClient.egg-info/PKG-INFO
RestfulClient.egg-info/SOURCES.txt
RestfulClient.egg-info/dependency_links.txt
RestfulClient.egg-info/requires.txt
RestfulClient.egg-info/top_level.txt
RestfulClient/api/__init__.py