Metadata-Version: 1.1
Name: RestfulClient
Version: 0.9.0
Summary: Generic RESTful API Client
Home-page: http://github.com/JamieCressey/python-restful-client
Author: Jamie Cressey
Author-email: jamiecressey89@gmail.com
License: UNKNOWN
Platform: UNKNOWN
Classifier: Development Status :: 5 - Production/Stable
Classifier: Intended Audience :: Developers
Classifier: License :: OSI Approved :: MIT License
Classifier: Operating System :: OS Independent
Classifier: Programming Language :: Python
Classifier: Programming Language :: Python :: 2.5
Classifier: Programming Language :: Python :: 2.6
Classifier: Programming Language :: Python :: 2.7
Classifier: Topic :: Software Development :: Libraries :: Python Modules
